pydygp/__init__.py
pydygp/gaussian_process/__init__.py
pydygp/gaussian_process/mogpr.py
pydygp/gradientkernels/__init__.py
pydygp/gradientkernels/gradientkernels.py
pydygp/kernels/__init__.py
pydygp/kernels/kernels.py
pydygp/liealgebras/__init__.py
pydygp/liealgebras/liealgebras.py
pydygp/linlatentforcemodels/__init__.py
pydygp/linlatentforcemodels/kalmanfilter.py
pydygp/linlatentforcemodels/kf_util.py
pydygp/linlatentforcemodels/lfmorder2.py
pydygp/linlatentforcemodels/mlfm.py
pydygp/linlatentforcemodels/mlfmadapgrad.py
pydygp/linlatentforcemodels/mlfmmixsa.py
pydygp/linlatentforcemodels/mlfmsamoe.py
pydygp/linlatentforcemodels/mlfmsamoe2.py
pydygp/linlatentforcemodels/mlfmsuccapprox.py
pydygp/linlatentforcemodels/util.py
pydygp/linlatentforcemodels/util_flymake.py
pydygp/probabilitydistributions/__init__.py
pydygp/probabilitydistributions/foo.py
pydygp/probabilitydistributions/probabilitydistributions.py
pydygp/pydygp_examples/__init__.py
pydygp/pydygp_examples/mocap_example.py
pydygp-0.2.3.3.dist-info/METADATA
pydygp-0.2.3.3.dist-info/WHEEL
pydygp-0.2.3.3.dist-info/top_level.txt
pydygp-0.2.3.3.dist-info/RECORD
