Metadata-Version: 2.1
Name: pydygp
Version: 0.2.3.3
Summary: UNKNOWN
Home-page: http://github.com/danieljtait/pydygp
Author: Daniel Tait
Author-email: tait.djk@gmail.com
License: MIT
Platform: UNKNOWN
Requires-Dist: numpy
Requires-Dist: scipy
Requires-Dist: matplotlib (>=2.2.0)
Requires-Dist: scikit-learn
Requires-Dist: autograd
